octo_pipeline_python/backends/cdk/__init__.py
octo_pipeline_python/backends/cdk/cdk_backend.py
octo_pipeline_python/backends/cdk/actions/__init__.py
octo_pipeline_python/backends/cdk/actions/cdk_build.py
octo_pipeline_python/backends/cdk/actions/cdk_build_layer.py
octo_pipeline_python/backends/cdk/actions/cdk_deploy.py
octo_pipeline_python/backends/cdk/actions/cdk_destroy.py
octo_pipeline_python/backends/cdk/common/__init__.py
octo_pipeline_python/backends/cdk/common/cdk_env.py
octo_pipeline_python/backends/cdk/common/cdk_stack.py
octo_pipeline_python/backends/cdk/models/__init__.py
octo_pipeline_python/backends/cdk/models/cdk_model.py
octo_pipeline_python/backends/cdk/utils/__init__.py
octo_pipeline_python/backends/cdk/utils/stack_name.py
octo_pipeline_backend_cdk_python-1.3.2.dist-info/LICENSE.txt
octo_pipeline_backend_cdk_python-1.3.2.dist-info/METADATA
octo_pipeline_backend_cdk_python-1.3.2.dist-info/README.md
octo_pipeline_backend_cdk_python-1.3.2.dist-info/WHEEL
octo_pipeline_backend_cdk_python-1.3.2.dist-info/top_level.txt
octo_pipeline_backend_cdk_python-1.3.2.dist-info/RECORD
